<annotation>
	<folder>Img_final</folder>
	<filename>Img_193.jpg</filename>
	<path>/Users/noor/thesis_local/Img_final/Img_193.jpg</path>
	<source>
		<database>Unknown</database>
	</source>
	<size>
		<width>720</width>
		<height>1280</height>
		<depth>3</depth>
	</size>
	<segmented>0</segmented>
	<object>
		<name>Light_Switch</name>
		<pose>Unspecified</pose>
		<truncated>0</truncated>
		<difficult>0</difficult>
		<bndbox>
			<xmin>284</xmin>
			<ymin>774</ymin>
			<xmax>342</xmax>
			<ymax>836</ymax>
		</bndbox>
	</object>
	<object>
		<name>Light_Switch</name>
		<pose>Unspecified</pose>
		<truncated>0</truncated>
		<difficult>0</difficult>
		<bndbox>
			<xmin>287</xmin>
			<ymin>841</ymin>
			<xmax>345</xmax>
			<ymax>900</ymax>
		</bndbox>
	</object>
</annotation>
